Metadata-Version: 2.1
Name: hazytod
Version: 0.0
Summary: tod
Author-email: karpenko.milorad@gmail.com
